LICENSE.txt
MANIFEST.in
README.rst
setup.py
immagine.egg-info/PKG-INFO
immagine.egg-info/SOURCES.txt
immagine.egg-info/dependency_links.txt
immagine.egg-info/top_level.txt
scripts/immagine
src/__init__.py
src/__main__.py
src/backcaller.py
src/base_tab.py
src/browser_tab.py
src/config.py
src/file_utils.py
src/gui.py
src/icons.py
src/image_browser.py
src/layout.py
src/new_thumbnailer.py
src/orchestrator.py
src/test.py
src/thumbnail.py
src/thumbnailers.py
src/toolbar_window.py
src/version.py
src/viewer_tab.py