Metadata-Version: 1.1
Name: immagine
Version: 0.7
Summary: Image viewer and browser with directory thumbnails
Home-page: https://github.com/mfnch/immagine
Author: Matteo Franchin
Author-email: fnch@users.sf.net
License: Apache License, Version 2.0
Keywords: image viewer,image browser,thumbnail
Platform: UNKNOWN
Classifier: Programming Language :: Python :: 2
Classifier: Programming Language :: Python :: 2.7
Classifier: Development Status :: 3 - Alpha
Classifier: Topic :: Multimedia :: Graphics :: Viewers
Classifier: License :: OSI Approved :: Apache Software License
